injectulate/__init__.py
injectulate/container.py
injectulate/errors.py
injectulate/test/__init__.py
injectulate/test/container_test.py
Injectulate-0.1.1.dist-info/LICENSE
Injectulate-0.1.1.dist-info/METADATA
Injectulate-0.1.1.dist-info/WHEEL
Injectulate-0.1.1.dist-info/top_level.txt
Injectulate-0.1.1.dist-info/RECORD
