Metadata-Version: 2.1
Name: Injectulate
Version: 0.1.1
Summary: Lightweight dependency injection container.
Author-email: Henrik Hjalmarsson <henrik.hjalmarsson.lazy@gmail.com>
License: GNU GENERAL PUBLIC LICENSE
Keywords: DI,Dependency Injection,IoC,Injection,Lightweight,Type annotation
Classifier: Development Status :: 3 - Alpha
Classifier: Intended Audience :: Developers
Classifier: License :: OSI Approved :: GNU General Public License v3 (GPLv3)
Classifier: Natural Language :: English
Classifier: Programming Language :: Python :: 3.11
Classifier: Topic :: Software Development :: Libraries
Classifier: Topic :: Utilities
Classifier: Typing :: Typed
Requires-Python: >=3.10
License-File: LICENSE
